PyQt6-stubs/Qsci.pyi
PyQt6-stubs/QtBluetooth.pyi
PyQt6-stubs/QtCharts.pyi
PyQt6-stubs/QtCore.pyi
PyQt6-stubs/QtDBus.pyi
PyQt6-stubs/QtDataVisualization.pyi
PyQt6-stubs/QtDesigner.pyi
PyQt6-stubs/QtGraphs.pyi
PyQt6-stubs/QtGraphsWidgets.pyi
PyQt6-stubs/QtGui.pyi
PyQt6-stubs/QtHelp.pyi
PyQt6-stubs/QtMultimedia.pyi
PyQt6-stubs/QtMultimediaWidgets.pyi
PyQt6-stubs/QtNetwork.pyi
PyQt6-stubs/QtNetworkAuth.pyi
PyQt6-stubs/QtNfc.pyi
PyQt6-stubs/QtOpenGL.pyi
PyQt6-stubs/QtOpenGLWidgets.pyi
PyQt6-stubs/QtPdf.pyi
PyQt6-stubs/QtPdfWidgets.pyi
PyQt6-stubs/QtPositioning.pyi
PyQt6-stubs/QtPrintSupport.pyi
PyQt6-stubs/QtQml.pyi
PyQt6-stubs/QtQuick.pyi
PyQt6-stubs/QtQuick3D.pyi
PyQt6-stubs/QtQuickWidgets.pyi
PyQt6-stubs/QtRemoteObjects.pyi
PyQt6-stubs/QtSensors.pyi
PyQt6-stubs/QtSerialPort.pyi
PyQt6-stubs/QtSpatialAudio.pyi
PyQt6-stubs/QtSql.pyi
PyQt6-stubs/QtStateMachine.pyi
PyQt6-stubs/QtSvg.pyi
PyQt6-stubs/QtSvgWidgets.pyi
PyQt6-stubs/QtTest.pyi
PyQt6-stubs/QtTextToSpeech.pyi
PyQt6-stubs/QtWebChannel.pyi
PyQt6-stubs/QtWebEngineCore.pyi
PyQt6-stubs/QtWebEngineQuick.pyi
PyQt6-stubs/QtWebEngineWidgets.pyi
PyQt6-stubs/QtWebSockets.pyi
PyQt6-stubs/QtWidgets.pyi
PyQt6-stubs/QtXml.pyi
PyQt6-stubs/sip.pyi
pyqt6_stubs-20250824.dist-info/licenses/LICENSE
pyqt6_stubs-20250824.dist-info/METADATA
pyqt6_stubs-20250824.dist-info/WHEEL
pyqt6_stubs-20250824.dist-info/top_level.txt
pyqt6_stubs-20250824.dist-info/RECORD
