Metadata-Version: 2.4
Name: PyQt6-stubs
Version: 20250824
Summary: Collections of stubs for the PyQt6 framework and its extensions.
Author-email: Blackteahamburger <blackteahamburger@outlook.com>
Maintainer-email: Blackteahamburger <blackteahamburger@outlook.com>
License-Expression: GPL-3.0
Project-URL: Homepage, https://github.com/blackteahamburger/PyQt6-stubs
Classifier: Development Status :: 5 - Production/Stable
Classifier: Intended Audience :: Developers
Classifier: Operating System :: OS Independent
Classifier: Programming Language :: Python :: 3
Classifier: Typing :: Stubs Only
Requires-Python: >=3.10
License-File: LICENSE
Provides-Extra: dev
Requires-Dist: ruff; extra == "dev"
Dynamic: license-file
